KaggleAutoAI/__init__.py
KaggleAutoAI/helper_function.py
KaggleAutoAI/automated_ai/__init__.py
KaggleAutoAI/automated_ai/algorithms/__init__.py
KaggleAutoAI/automated_ai/algorithms/complexity_level0.py
KaggleAutoAI/automated_ai/algorithms/complexity_level1.py
KaggleAutoAI/automated_ai/classification_automated/__init__.py
KaggleAutoAI/automated_ai/classification_automated/cat_automated.py
KaggleAutoAI/automated_ai/classification_automated/extra_trees.py
KaggleAutoAI/automated_ai/classification_automated/gradient_boosting_automated.py
KaggleAutoAI/automated_ai/classification_automated/hist_gradient_automated.py
KaggleAutoAI/automated_ai/classification_automated/lgb_automated.py
KaggleAutoAI/automated_ai/classification_automated/logistic_regression_automated.py
KaggleAutoAI/automated_ai/classification_automated/random_forest_automated.py
KaggleAutoAI/automated_ai/classification_automated/xgb_automated.py
KaggleAutoAI/automated_ai/regression_automated/__init__.py
KaggleAutoAI/automated_ai/regression_automated/cat_automated.py
KaggleAutoAI/automated_ai/regression_automated/gradient_boosting_automated.py
KaggleAutoAI/automated_ai/regression_automated/lgb_automated.py
KaggleAutoAI/automated_ai/regression_automated/xgb_automated.py
KaggleAutoAI/classification/__init__.py
KaggleAutoAI/classification/metrics.py
KaggleAutoAI/classification/models/__init__.py
KaggleAutoAI/classification/models/cat.py
KaggleAutoAI/classification/models/extra_trees.py
KaggleAutoAI/classification/models/gradient_boosting.py
KaggleAutoAI/classification/models/hist_gradient.py
KaggleAutoAI/classification/models/kneighbours.py
KaggleAutoAI/classification/models/light_lgb.py
KaggleAutoAI/classification/models/linear_svc.py
KaggleAutoAI/classification/models/logistic_regression.py
KaggleAutoAI/classification/models/random_forest.py
KaggleAutoAI/classification/models/sgd_classifier.py
KaggleAutoAI/classification/models/svc.py
KaggleAutoAI/classification/models/xgb.py
PatryksAutoAI-1.6.2.dist-info/METADATA
PatryksAutoAI-1.6.2.dist-info/WHEEL
PatryksAutoAI-1.6.2.dist-info/top_level.txt
PatryksAutoAI-1.6.2.dist-info/RECORD
