Metadata-Version: 2.1
Name: PatryksAutoAI
Version: 1.6.2
Summary: Auto_AI_patryk
Author: patryk
Author-email: lyczkopatryk1@gmail.com
Keywords: python,machine_learning,auto
Classifier: Development Status :: 1 - Planning
Classifier: Intended Audience :: Developers
Classifier: Programming Language :: Python :: 3
Classifier: Operating System :: Unix
Classifier: Operating System :: MacOS :: MacOS X
Classifier: Operating System :: Microsoft :: Windows
Classifier: Operating System :: POSIX :: Linux
Requires-Dist: scipy (>=1.7.2)
Requires-Dist: seaborn (>=0.12.2)
Requires-Dist: scikit-learn (>=1.0.2)
Requires-Dist: pandas (<1.6.0,>=1.3.5)
Requires-Dist: matplotlib (>=3.5.3)
Requires-Dist: numpy (>=1.21.6)
Requires-Dist: xgboost (>=1.6.2)
Requires-Dist: catboost (>=1.1.1)
Requires-Dist: lightgbm (>=3.3.2)
Requires-Dist: optuna (>=3.1.0)
Requires-Dist: emoji (>=2.2.0)
Requires-Dist: nltk (>=3.2.4)
Requires-Dist: pyspellchecker (>=0.7.2)
Requires-Dist: transformers (<4.29.0,>=4.27.3)
Requires-Dist: joblib (>=1.1.0)
